MANIFEST.in
README.txt
setup.cfg
setup.py
docs/HISTORY.txt
docs/INSTALL.txt
docs/LICENSE.GPL
docs/LICENSE.txt
ityou/__init__.py
ityou.notify.egg-info/PKG-INFO
ityou.notify.egg-info/SOURCES.txt
ityou.notify.egg-info/dependency_links.txt
ityou.notify.egg-info/entry_points.txt
ityou.notify.egg-info/namespace_packages.txt
ityou.notify.egg-info/not-zip-safe
ityou.notify.egg-info/paster_plugins.txt
ityou.notify.egg-info/requires.txt
ityou.notify.egg-info/top_level.txt
ityou/notify/__init__.py
ityou/notify/configure.zcml
ityou/notify/dbapi.py
ityou/notify/interfaces.py
ityou/notify/tests.py
ityou/notify/translate.sh
ityou/notify/browser/__init__.py
ityou/notify/browser/configure.zcml
ityou/notify/browser/controlpanel.py
ityou/notify/browser/notification_sender.py
ityou/notify/browser/images/ityou-esi-notify-icon.png
ityou/notify/locales/ityou.notify.pot
ityou/notify/locales/de/LC_MESSAGES/ityou.notify.po
ityou/notify/locales/en/LC_MESSAGES/ityou.notify.po
ityou/notify/profiles/default/browserlayer.xml
ityou/notify/profiles/default/controlpanel.xml
ityou/notify/profiles/default/metadata.xml
ityou/notify/profiles/default/registry.xml