Metadata-Version: 1.1
Name: ityou.notify
Version: 1.3.1
Summary: Sends E-Mails on changes
Home-page: http://www.ityou.de/esi/
Author: ITYOU/LM
Author-email: lm@ityou.de
License: GPL
Platform: UNKNOWN
Classifier: Framework :: Plone
Classifier: Programming Language :: Python
